{
  "date": "2026-07-23",
  "indices": {
    "sp500": {
      "close": 7408.3,
      "prev_close": 7498.96,
      "change_pct": -1.21,
      "pct_52w": 84.9
    },
    "nasdaq100": {
      "close": 28454.81,
      "prev_close": 28998.1,
      "change_pct": -1.87,
      "pct_52w": 71.5
    },
    "russell": {
      "close": 2940.16,
      "prev_close": 2959.94,
      "change_pct": -0.67,
      "pct_52w": 88.2
    },
    "vix": {
      "close": 18.7,
      "prev_close": 16.64,
      "change_pct": 12.38,
      "pct_52w": 24.3
    }
  },
  "rates": {
    "us2y": {
      "value": 4.31,
      "date": "2026-07-22",
      "change_pct": 1.17,
      "prev_value": 4.26
    },
    "us10y": {
      "value": 4.67,
      "date": "2026-07-22",
      "change_pct": 0.86,
      "prev_value": 4.63
    },
    "tips10y": {
      "value": 2.39,
      "date": "2026-07-22",
      "change_pct": 0.84,
      "prev_value": 2.37
    }
  },
  "spreads": {
    "us2s10s": {
      "value": 0.34,
      "date": "2026-07-23",
      "change_pct": -5.56,
      "prev_value": 0.36
    },
    "us5s30s": {
      "value": null,
      "date": null
    },
    "hy_spread": {
      "value": 2.68,
      "date": "2026-07-22",
      "change_pct": -0.37,
      "prev_value": 2.69
    },
    "fra_ois": {
      "value": 3.63,
      "date": "2026-07-22",
      "change_pct": 0.0,
      "prev_value": 3.63
    }
  },
  "fx": {
    "dxy": {
      "value": 120.5315,
      "date": "2026-07-17",
      "change_pct": 0.17,
      "prev_value": 120.331
    },
    "usdkrw": {
      "close": 1474.75,
      "prev_close": 1475.63,
      "change_pct": -0.06,
      "pct_52w": 57.4
    },
    "usdjpy": {
      "close": 163.84,
      "prev_close": 163.08,
      "change_pct": 0.47,
      "pct_52w": 99.2
    },
    "eurusd": {
      "close": 1.14,
      "prev_close": 1.14,
      "change_pct": 0.0,
      "pct_52w": 10.7
    }
  },
  "commodities": {
    "wti": {
      "close": 92.15,
      "prev_close": 86.83,
      "change_pct": 6.13,
      "pct_52w": 57.6
    },
    "gold": {
      "close": 4051.3,
      "prev_close": 4146.9,
      "change_pct": -2.31,
      "pct_52w": 33.9
    },
    "copper": {
      "close": 6.33,
      "prev_close": 6.45,
      "change_pct": -1.86,
      "pct_52w": 86.2
    }
  },
  "liquidity": {
    "fed_bs": {
      "value": 6747378.0,
      "date": "2026-07-22",
      "change_pct": 0.06,
      "prev_value": 6743028.0
    },
    "rrp": {
      "value": 0.904,
      "date": "2026-07-23",
      "change_pct": 140.43,
      "prev_value": 0.376
    },
    "m2": {
      "value": 23052.3,
      "date": "2026-05-01",
      "change_pct": 1.09,
      "prev_value": 22804.5
    }
  },
  "sectors": {
    "tech": {
      "close": 178.45,
      "change_pct": -1.01,
      "change_4w": -2.51,
      "pct_52w": 72.1
    },
    "financials": {
      "close": 55.83,
      "change_pct": -0.39,
      "change_4w": 3.93,
      "pct_52w": 88.2
    },
    "energy": {
      "close": 59.38,
      "change_pct": 0.3,
      "change_4w": 10.85,
      "pct_52w": 83.7
    },
    "utilities": {
      "close": 46.19,
      "change_pct": 0.57,
      "change_4w": 1.43,
      "pct_52w": 83.5
    },
    "healthcare": {
      "close": 161.44,
      "change_pct": 1.26,
      "change_4w": 5.28,
      "pct_52w": 89.5
    },
    "consumer_disc": {
      "close": 108.76,
      "change_pct": -4.61,
      "change_4w": -5.48,
      "pct_52w": 19.4
    },
    "industrials": {
      "close": 181.94,
      "change_pct": 1.73,
      "change_4w": 0.96,
      "pct_52w": 88.9
    },
    "materials": {
      "close": 50.29,
      "change_pct": -1.04,
      "change_4w": -1.7,
      "pct_52w": 72.1
    }
  },
  "macro": {
    "cpi_yoy": {
      "value": 3.73,
      "date": "2026-06-01",
      "change_pct": null
    },
    "core_cpi": {
      "value": 2.81,
      "date": "2026-06-01",
      "change_pct": null
    },
    "unemployment": {
      "value": 4.2,
      "date": "2026-06-01",
      "change_pct": -2.33,
      "prev_value": 4.3
    },
    "pce": {
      "value": 4.07,
      "date": "2026-05-01",
      "change_pct": null
    },
    "gdp_growth": {
      "value": 2.1,
      "date": "2026-01-01",
      "change_pct": 320.0,
      "prev_value": 0.5
    },
    "ism_mfg": {
      "value": 44.8,
      "date": "2026-05-01",
      "change_pct": -10.04,
      "prev_value": 49.8
    },
    "ism_svc": {
      "value": 98.91297,
      "date": "2024-01-01",
      "change_pct": 0.82,
      "prev_value": 98.1097
    }
  },
  "sentiment": {
    "fear_greed": {
      "score": 44,
      "rating": "Fear"
    },
    "skew": {
      "close": 145.95,
      "change_pct": -2.82,
      "signal": "yellow",
      "combo_signal": "orange",
      "combo_label": "숨겨진경고(VIX↓+Skew↑)"
    }
  },
  "calendar": [
    {
      "date": "2026-07-29",
      "event": "FOMC 금리 결정",
      "category": "fed",
      "impact": "high"
    },
    {
      "date": "2026-07-30",
      "event": "FOMC 기자회견",
      "category": "fed",
      "impact": "high"
    },
    {
      "date": "2026-07-30",
      "event": "GDP 속보치 (Q2 2026)",
      "category": "gdp",
      "impact": "high"
    },
    {
      "date": "2026-07-31",
      "event": "PCE 발표 (6월)",
      "category": "pce",
      "impact": "high"
    },
    {
      "date": "2026-08-07",
      "event": "고용보고서 (7월)",
      "category": "jobs",
      "impact": "high"
    },
    {
      "date": "2026-08-12",
      "event": "CPI 발표 (7월)",
      "category": "cpi",
      "impact": "high"
    },
    {
      "date": "2026-08-28",
      "event": "PCE 발표 (7월)",
      "category": "pce",
      "impact": "high"
    },
    {
      "date": "2026-09-04",
      "event": "고용보고서 (8월)",
      "category": "jobs",
      "impact": "high"
    }
  ],
  "news": [
    {
      "title": "The August stock-market slump is a myth — so why does Wall Street keep repeating it?",
      "url": "https://www.marketwatch.com/story/the-august-stock-market-slump-is-a-myth-so-why-does-wall-street-keep-repeating-it-bc47db44?mod=mw_rss_topstories",
      "source": "MarketWatch",
      "published": "Thu, 23 Jul 2026 22:12:00 GMT",
      "title_ko": "8월 주식시장의 폭락은 신화다 — 월 스트리트는 왜 계속 반복하는가"
    },
    {
      "title": "S&P 500 flashes sell signals — options traders are bracing for wild swings in Apple, Meta and Microsoft",
      "url": "https://www.marketwatch.com/story/s-p-500-flashes-sell-signals-options-traders-are-bracing-for-wild-swings-in-apple-meta-and-microsoft-83ff7d65?mod=mw_rss_topstories",
      "source": "MarketWatch",
      "published": "Thu, 23 Jul 2026 22:03:00 GMT",
      "title_ko": "S&P 500은 매도 신호를 보이고 있다 — 옵션 거래자들은 애플, 메타, 마이크로소프트의 거대한 변동에 대비하고 있다"
    },
    {
      "title": "Yes, the AI stock selloff looks terrifying. But it might actually save the bull market.",
      "url": "https://www.marketwatch.com/story/yes-the-ai-stock-selloff-looks-terrifying-but-it-might-actually-save-the-bull-market-3bef59be?mod=mw_rss_topstories",
      "source": "MarketWatch",
      "published": "Thu, 23 Jul 2026 22:02:00 GMT",
      "title_ko": "예, AI 주식 매도는 두려워 보이지만 실제로 황소 시장을 구할 수도 있다"
    },
    {
      "title": "The stock market’s calm is cracking. Here’s how to prepare for an August shock.",
      "url": "https://www.marketwatch.com/story/the-stock-markets-calm-surface-is-cracking-heres-how-to-prepare-for-an-august-shock-7d655813?mod=mw_rss_topstories",
      "source": "MarketWatch",
      "published": "Thu, 23 Jul 2026 21:53:00 GMT",
      "title_ko": "주식시장의 평온은 깨지고 있다. 8월 충격에 대비하는 방법은 다음과 같다"
    },
    {
      "title": "Trump rolls out a new wave of global tariffs. Here are the latest rates.",
      "url": "https://www.marketwatch.com/story/trump-rolls-out-a-new-wave-of-tariffs-here-are-the-latest-rates-449af1d3?mod=mw_rss_topstories",
      "source": "MarketWatch",
      "published": "Thu, 23 Jul 2026 21:50:00 GMT",
      "title_ko": "트럼프는 새로운 세계적인 관세의 물결을 내놓았다. 최신 세율은 다음과 같다"
    },
    {
      "title": "Trump to slap 'sweeping' new tariffs on 60 trade partners as global duties expire",
      "url": "https://www.cnbc.com/2026/07/23/trump-tariffs-trade-deadline.html",
      "source": "CNBC",
      "published": "Thu, 23 Jul 2026 21:43:10 GMT",
      "title_ko": "트럼프는 60개의 무역 파트너에 대한 새로운 관세를 부과할 것이다"
    },
    {
      "title": "Japan core inflation rate in June creeps up from 4-year low as higher oil prices bite",
      "url": "https://www.cnbc.com/2026/07/24/japan-cpi-june-inflation-oil-prices-yen.html",
      "source": "CNBC",
      "published": "Thu, 23 Jul 2026 23:48:04 GMT",
      "title_ko": "일본의 6월 핵심 인플레이션율은 4년 만에 최고치에서 조금 상승했다"
    },
    {
      "title": "Shortsighted stock market can no longer brush off war: 'It's too hard to ignore $100 oil'",
      "url": "https://www.cnbc.com/2026/07/23/short-sighted-stock-market-can-no-longer-brush-off-war-investors-say.html",
      "source": "CNBC",
      "published": "Thu, 23 Jul 2026 19:19:01 GMT",
      "title_ko": "앞을 못 보는 주식시장은 더 이상 전쟁을 무시할 수 없다"
    },
    {
      "title": "Amazon and Microsoft pivot cloud gaming strategies to target different players",
      "url": "https://www.cnbc.com/2026/07/23/amazon-microsoft-cloud-gaming.html",
      "source": "CNBC",
      "published": "Thu, 23 Jul 2026 20:06:50 GMT",
      "title_ko": "아마존과 마이크로소프트는 다른 사용자를 대상으로 클라우드 게임 전략을 전환했다"
    },
    {
      "title": "10-year Treasury yield rises to highest since January 2025 as surging oil rekindles inflation fear",
      "url": "https://www.cnbc.com/2026/07/23/treasury-yields-oil-prices-jobless-claims.html",
      "source": "CNBC",
      "published": "Thu, 23 Jul 2026 20:30:50 GMT",
      "title_ko": "10년 만기 미국 국채 금리는 2025년 1월 이후 최고치로 상승했다"
    },
    {
      "title": "Odds of Federal Reserve rate hike surge as oil prices rip higher",
      "url": "https://www.cnbc.com/2026/07/23/fed-interest-rate-odds-oil-jobless-claims.html",
      "source": "CNBC",
      "published": "Thu, 23 Jul 2026 20:25:28 GMT",
      "title_ko": "연방 준비 제도 금리 인상의 가능성이 높아졌다"
    },
    {
      "title": "As the S&P 500 sells off, traders eye key 'risk pivot' level",
      "url": "https://www.cnbc.com/2026/07/23/as-the-sp-500-sells-off-traders-eye-key-risk-pivot-level.html",
      "source": "CNBC",
      "published": "Thu, 23 Jul 2026 20:22:32 GMT",
      "title_ko": "S&P 500이 매도되면서 거래자들은 중요한 리스크 전환 수준을 주시하고 있다"
    }
  ]
}